derpcache/__init__.py
derpcache/_cache.py
tests/__init__.py
tests/test_cache.py
derpcache-0.1.0.dist-info/LICENCE.md
derpcache-0.1.0.dist-info/METADATA
derpcache-0.1.0.dist-info/WHEEL
derpcache-0.1.0.dist-info/top_level.txt
derpcache-0.1.0.dist-info/RECORD
