Metadata-Version: 2.1
Name: derpcache
Version: 0.1.0
Summary: A simple pickle-based caching utility.
Author: Ben Johnson
Author-email: bkitej@gmail.com
License: GPL-3
License-File: LICENCE.md
Provides-Extra: dev
Requires-Dist: commitizen ; extra == 'dev'
Requires-Dist: pre-commit ; extra == 'dev'
Provides-Extra: lint
Requires-Dist: black ; extra == 'lint'
Requires-Dist: flakeheaven ; extra == 'lint'
Requires-Dist: mypy ; extra == 'lint'
Requires-Dist: types-setuptools ; extra == 'lint'
Provides-Extra: test
Requires-Dist: faker ; extra == 'test'
Requires-Dist: pytest ; extra == 'test'
Requires-Dist: pytest-freezegun ; extra == 'test'
